odoo/addons/project_task_add_very_high/README.rst
odoo/addons/project_task_add_very_high/__init__.py
odoo/addons/project_task_add_very_high/__manifest__.py
odoo/addons/project_task_add_very_high/hooks.py
odoo/addons/project_task_add_very_high/i18n/ar.po
odoo/addons/project_task_add_very_high/i18n/ca.po
odoo/addons/project_task_add_very_high/i18n/de.po
odoo/addons/project_task_add_very_high/i18n/el.po
odoo/addons/project_task_add_very_high/i18n/es.po
odoo/addons/project_task_add_very_high/i18n/es_CR.po
odoo/addons/project_task_add_very_high/i18n/es_MX.po
odoo/addons/project_task_add_very_high/i18n/es_VE.po
odoo/addons/project_task_add_very_high/i18n/fi.po
odoo/addons/project_task_add_very_high/i18n/fr.po
odoo/addons/project_task_add_very_high/i18n/gl.po
odoo/addons/project_task_add_very_high/i18n/hr.po
odoo/addons/project_task_add_very_high/i18n/hr_HR.po
odoo/addons/project_task_add_very_high/i18n/hu.po
odoo/addons/project_task_add_very_high/i18n/it.po
odoo/addons/project_task_add_very_high/i18n/ja.po
odoo/addons/project_task_add_very_high/i18n/lt.po
odoo/addons/project_task_add_very_high/i18n/lv.po
odoo/addons/project_task_add_very_high/i18n/mk.po
odoo/addons/project_task_add_very_high/i18n/mn.po
odoo/addons/project_task_add_very_high/i18n/nl.po
odoo/addons/project_task_add_very_high/i18n/nl_NL.po
odoo/addons/project_task_add_very_high/i18n/pl.po
odoo/addons/project_task_add_very_high/i18n/pt.po
odoo/addons/project_task_add_very_high/i18n/pt_BR.po
odoo/addons/project_task_add_very_high/i18n/pt_PT.po
odoo/addons/project_task_add_very_high/i18n/ro.po
odoo/addons/project_task_add_very_high/i18n/sl.po
odoo/addons/project_task_add_very_high/i18n/sv.po
odoo/addons/project_task_add_very_high/i18n/tr.po
odoo/addons/project_task_add_very_high/i18n/uk.po
odoo/addons/project_task_add_very_high/i18n/zh_CN.po
odoo/addons/project_task_add_very_high/models/__init__.py
odoo/addons/project_task_add_very_high/models/project_task.py
odoo11_addon_project_task_add_very_high-11.0.1.0.0.dist-info/DESCRIPTION.rst
odoo11_addon_project_task_add_very_high-11.0.1.0.0.dist-info/METADATA
odoo11_addon_project_task_add_very_high-11.0.1.0.0.dist-info/RECORD
odoo11_addon_project_task_add_very_high-11.0.1.0.0.dist-info/WHEEL
odoo11_addon_project_task_add_very_high-11.0.1.0.0.dist-info/metadata.json
odoo11_addon_project_task_add_very_high-11.0.1.0.0.dist-info/top_level.txt
